odoo/addons/stock_location_orderpoint_cleanup/README.rst
odoo/addons/stock_location_orderpoint_cleanup/__init__.py
odoo/addons/stock_location_orderpoint_cleanup/__manifest__.py
odoo/addons/stock_location_orderpoint_cleanup/i18n/it.po
odoo/addons/stock_location_orderpoint_cleanup/i18n/stock_location_orderpoint_cleanup.pot
odoo/addons/stock_location_orderpoint_cleanup/models/__init__.py
odoo/addons/stock_location_orderpoint_cleanup/models/stock_location_orderpoint.py
odoo/addons/stock_location_orderpoint_cleanup/models/stock_picking.py
odoo/addons/stock_location_orderpoint_cleanup/readme/CONFIGURE.md
odoo/addons/stock_location_orderpoint_cleanup/readme/CONTEXT.md
odoo/addons/stock_location_orderpoint_cleanup/readme/CONTRIBUTORS.md
odoo/addons/stock_location_orderpoint_cleanup/readme/DESCRIPTION.md
odoo/addons/stock_location_orderpoint_cleanup/readme/USAGE.md
odoo/addons/stock_location_orderpoint_cleanup/security/security.xml
odoo/addons/stock_location_orderpoint_cleanup/static/description/icon.png
odoo/addons/stock_location_orderpoint_cleanup/static/description/index.html
odoo/addons/stock_location_orderpoint_cleanup/tests/__init__.py
odoo/addons/stock_location_orderpoint_cleanup/tests/test_location_orderpoint_cleanup.py
odoo/addons/stock_location_orderpoint_cleanup/views/stock_location_orderpoint.xml
odoo/addons/stock_location_orderpoint_cleanup/wizards/__init__.py
odoo/addons/stock_location_orderpoint_cleanup/wizards/stock_location_orderpoint_cleanup.py
odoo/addons/stock_location_orderpoint_cleanup/wizards/stock_location_orderpoint_cleanup.xml
odoo_addon_stock_location_orderpoint_cleanup-16.0.1.0.0.10.dist-info/METADATA
odoo_addon_stock_location_orderpoint_cleanup-16.0.1.0.0.10.dist-info/WHEEL
odoo_addon_stock_location_orderpoint_cleanup-16.0.1.0.0.10.dist-info/top_level.txt
odoo_addon_stock_location_orderpoint_cleanup-16.0.1.0.0.10.dist-info/RECORD
