Metadata-Version: 2.1
Name: odoo-addon-stock_location_orderpoint_cleanup
Version: 16.0.1.0.0.10
Summary: This module allows to clean moves generated by orderpoint
Home-page: https://github.com/OCA/stock-logistics-orderpoint
Author: ACSONE SA/NV,Odoo Community Association (OCA)
Author-email: support@odoo-community.org
License: AGPL-3
Classifier: Programming Language :: Python
Classifier: Framework :: Odoo
Classifier: Framework :: Odoo :: 16.0
Classifier: License :: OSI Approved :: GNU Affero General Public License v3
Requires-Python: >=3.10
Requires-Dist: odoo-addon-base-partition<16.1dev,>=16.0dev
Requires-Dist: odoo-addon-queue-job<16.1dev,>=16.0dev
Requires-Dist: odoo-addon-stock-location-orderpoint<16.1dev,>=16.0dev
Requires-Dist: odoo<16.1dev,>=16.0a
